{
  "note_angles": {
    "0": { "note_name": "C", "angle": 0 },
    "1": { "note_name": "G", "angle": 30 },
    "2": { "note_name": "D", "angle": 60 },
    "3": { "note_name": "A", "angle": 90 },
    "4": { "note_name": "E", "angle": 120 },
    "5": { "note_name": "B", "angle": 150 },
    "6": { "note_name": "F#", "angle": 180 },
    "7": { "note_name": "C#", "angle": 210 },
    "8": { "note_name": "G#", "angle": 240 },
    "9": { "note_name": "D#", "angle": 270 },
    "10": { "note_name": "A#", "angle": 300 },
    "11": { "note_name": "F", "angle": 330 }
  },
  "instrument names": {
    "1": "Acoustic Grand Piano",
    "2": "Bright Acoustic Piano",
    "3": "Electric Grand Piano",
    "4": "Honky-tonk Piano",
    "5": "Electric Piano 1",
    "6": "Electric Piano 2",
    "7": "Harpsichord",
    "8": "Clavinet",
    "9": "Celesta",
    "10": "Glockenspiel",
    "11": "Music Box",
    "12": "Vibraphone",
    "13": "Marimba",
    "14": "Xylophone",
    "15": "Tubular Bells",
    "16": "Dulcimer",
    "17": "Drawbar Organ",
    "18": "Percussive Organ",
    "19": "Rock Organ",
    "20": "Church Organ",
    "21": "Reed Organ",
    "22": "Accordion",
    "23": "Harmonica",
    "24": "Tango Accordion",
    "25": "Acoustic Guitar (nylon)",
    "26": "Acoustic Guitar (steel)",
    "27": "Electric Guitar (jazz)",
    "28": "Electric Guitar (clean)",
    "29": "Electric Guitar (muted)",
    "30": "Overdriven Guitar",
    "31": "Distortion Guitar",
    "32": "Guitar harmonics",
    "33": "Acoustic Bass",
    "34": "Electric Bass (finger)",
    "35": "Electric Bass (pick)",
    "36": "Fretless Bass",
    "37": "Slap Bass 1",
    "38": "Slap Bass 2",
    "39": "Synth Bass 1",
    "40": "Synth Bass 2",
    "41": "Violin",
    "42": "Viola",
    "43": "Cello",
    "44": "Contrabass",
    "45": "Tremolo Strings",
    "46": "Pizzicato Strings",
    "47": "Orchestral Harp",
    "48": "Timpani",
    "49": "String Ensemble 1",
    "50": "String Ensemble 2",
    "51": "Synth Strings 1",
    "52": "Synth Strings 2",
    "53": "Choir Aahs",
    "54": "Voice Oohs",
    "55": "Synth Voice",
    "56": "Orchestra Hit",
    "57": "Trumpet",
    "58": "Trombone",
    "59": "Tuba",
    "60": "Muted Trumpet",
    "61": "French Horn",
    "62": "Brass Section",
    "63": "Synth Brass 1",
    "64": "Synth Brass 2",
    "65": "Soprano Sax",
    "66": "Alto Sax",
    "67": "Tenor Sax",
    "68": "Baritone Sax",
    "69": "Oboe",
    "70": "English Horn",
    "71": "Bassoon",
    "72": "Clarinet",
    "73": "Piccolo",
    "74": "Flute",
    "75": "Recorder",
    "76": "Pan Flute",
    "77": "Blown Bottle",
    "78": "Shakuhachi",
    "79": "Whistle",
    "80": "Ocarina",
    "81": "Lead 1 (square)",
    "82": "Lead 2 (sawtooth)",
    "83": "Lead 3 (calliope)",
    "84": "Lead 4 (chiff)",
    "85": "Lead 5 (charang)",
    "86": "Lead 6 (voice)",
    "87": "Lead 7 (fifths)",
    "88": "Lead 8 (bass + lead)",
    "89": "Pad 1 (new age)",
    "90": "Pad 2 (warm)",
    "91": "Pad 3 (polysynth)",
    "92": "Pad 4 (choir)",
    "93": "Pad 5 (bowed)",
    "94": "Pad 6 (metallic)",
    "95": "Pad 7 (halo)",
    "96": "Pad 8 (sweep)",
    "97": "FX 1 (rain)",
    "98": "FX 2 (soundtrack)",
    "99": "FX 3 (crystal)",
    "100": "FX 4 (atmosphere)",
    "101": "FX 5 (brightness)",
    "102": "FX 6 (goblins)",
    "103": "FX 7 (echoes)",
    "104": "FX 8 (sci-fi)",
    "105": "Sitar",
    "106": "Banjo",
    "107": "Shamisen",
    "108": "Koto",
    "109": "Kalimba",
    "110": "Bag pipe",
    "111": "Fiddle",
    "112": "Shanai",
    "113": "Tinkle Bell",
    "114": "Agogo",
    "115": "Steel Drums",
    "116": "Woodblock",
    "117": "Taiko Drum",
    "118": "Melodic Tom",
    "119": "Synth Drum",
    "120": "Reverse Cymbal",
    "121": "Guitar Fret Noise",
    "122": "Breath Noise",
    "123": "Seashore",
    "124": "Bird Tweet",
    "125": "Telephone Ring",
    "126": "Helicopter",
    "127": "Applause",
    "128": "Gunshot"
  },
  "colors":     {"#aec934",
  "#9159de",
  "#77bf3a",
  "#4667e6",
  "#51cb5e",
  "#9b40b5",
  "#359f34",
  "#cb6ae3",
  "#82a51c",
  "#8475ef",
  "#b8b733",
  "#3c4dbb",
  "#e6a01e",
  "#4c7ff1",
  "#d9b637",
  "#6243b2",
  "#75b150",
  "#bd31a2",
  "#4bb871",
  "#ea59ba",
  "#5e8d26",
  "#7a55c3",
  "#a3bf60",
  "#385fcb",
  "#e38421",
  "#4691eb",
  "#ea6e2e",
  "#554baa",
  "#de9b36",
  "#9e7ee9",
  "#767c16",
  "#da68c9",
  "#357226",
  "#c12d8d",
  "#53cd98",
  "#e83889",
  "#479046",
  "#d584e5",
  "#445a06",
  "#76409a",
  "#a88f25",
  "#6168c5",
  "#b77f1e",
  "#3e6cba",
  "#c73e16",
  "#3ccde4",
  "#dc3f30",
  "#4cd2c3",
  "#e73667",
  "#3c9e81",
  "#d5334a",
  "#36b1da",
  "#b45618",
  "#5caee2",
  "#ad3b26",
  "#3aadb2",
  "#ef6456",
  "#2b5a9b",
  "#e5ad53",
  "#644999",
  "#9c9f44",
  "#8f63bb",
  "#576c1c",
  "#9d91e8",
  "#8d6c12",
  "#505099",
  "#ceb863",
  "#9e4793",
  "#8db773",
  "#af3274",
  "#428f5c",
  "#ca436c",
  "#7ec095",
  "#e072af",
  "#235e31",
  "#ec6c93",
  "#115e41",
  "#cc85ce",
  "#788c3b",
  "#7a488d",
  "#b9b676",
  "#6f64a6",
  "#df8e50",
  "#377cb1",
  "#a86828",
  "#829fdd",
  "#9a4f20",
  "#6a77b1",
  "#5b5b10",
  "#987dc0",
  "#7b7a30",
  "#d5a0d8",
  "#415a1f",
  "#ab699a",
  "#367042",
  "#9d3757",
  "#226a4d",
  "#bd4b4d",
  "#2f7b63",
  "#d77452",
  "#4a5589",
  "#ae8c49",
  "#8b4772",
  "#536c31",
  "#e58d9e",
  "#525620",
  "#ea8a7b",
  "#646831",
  "#bb6272",
  "#7c8a4f",
  "#8d4a57",
  "#695711",
  "#dfa777",
  "#704b0c",
  "#a95b4b",
  "#847037",
  "#874327",
  "#ab7950",
  "#8b6325",
  "#895a33"}